infotr/__init__.py
infotr/__main__.py
infotr/infotr.py
infotr-1.0.0.dist-info/LICENSE
infotr-1.0.0.dist-info/METADATA
infotr-1.0.0.dist-info/WHEEL
infotr-1.0.0.dist-info/entry_points.txt
infotr-1.0.0.dist-info/top_level.txt
infotr-1.0.0.dist-info/RECORD
