Metadata-Version: 2.1
Name: infotr
Version: 1.0.0
Summary: A traceroute tool that also displays IP information 
Home-page: https://github.com/k4yt3x/infotr
Author: K4YT3X
Author-email: k4yt3x@k4yt3x.com
License: GNU General Public License v3.0
Platform: UNKNOWN
Classifier: Topic :: System :: Networking
Classifier: Environment :: Console
Classifier: Programming Language :: Python
Classifier: Programming Language :: Python :: 3
Classifier: Operating System :: OS Independent
Requires-Python: >=3.6
Requires-Dist: scapy
Requires-Dist: requests
